vose/__init__.pxd
vose/__init__.py
vose/sampler.pxd
vose/sampler.pyx
vose-0.1.1.dist-info/LICENSE
vose-0.1.1.dist-info/METADATA
vose-0.1.1.dist-info/WHEEL
vose-0.1.1.dist-info/RECORD
