Metadata-Version: 2.3
Name: vose
Version: 0.1.1
Summary: Cython implementation of Vose's Alias method.
License: MIT
Author: Max Halford
Author-email: maxhalford25@gmail.com
Requires-Python: >=3.11
Classifier: License :: OSI Approved :: MIT License
Classifier: Programming Language :: Python :: 3
Classifier: Programming Language :: Python :: 3.11
Classifier: Programming Language :: Python :: 3.12
Classifier: Programming Language :: Python :: 3.13
Provides-Extra: dev
Requires-Dist: numpy
Project-URL: Homepage, https://github.com/MaxHalford/vose
